vis4d/__init__.py
vis4d/__main__.py
vis4d/common/__init__.py
vis4d/common/array.py
vis4d/common/ckpt.py
vis4d/common/dict.py
vis4d/common/distributed.py
vis4d/common/imports.py
vis4d/common/logging.py
vis4d/common/named_tuple.py
vis4d/common/prettyprint.py
vis4d/common/progress.py
vis4d/common/slurm.py
vis4d/common/time.py
vis4d/common/typing.py
vis4d/common/util.py
vis4d/config/__init__.py
vis4d/config/config_dict.py
vis4d/config/registry.py
vis4d/config/show_connection.py
vis4d/config/sweep.py
vis4d/config/typing.py
vis4d/data/__init__.py
vis4d/data/cbgs.py
vis4d/data/const.py
vis4d/data/data_pipe.py
vis4d/data/iterable.py
vis4d/data/loader.py
vis4d/data/reference.py
vis4d/data/resample.py
vis4d/data/samplers.py
vis4d/data/typing.py
vis4d/data/datasets/__init__.py
vis4d/data/datasets/base.py
vis4d/data/datasets/bdd100k.py
vis4d/data/datasets/coco.py
vis4d/data/datasets/imagenet.py
vis4d/data/datasets/nuscenes.py
vis4d/data/datasets/nuscenes_detection.py
vis4d/data/datasets/nuscenes_mono.py
vis4d/data/datasets/nuscenes_trajectory.py
vis4d/data/datasets/s3dis.py
vis4d/data/datasets/scalabel.py
vis4d/data/datasets/shift.py
vis4d/data/datasets/torchvision.py
vis4d/data/datasets/util.py
vis4d/data/io/__init__.py
vis4d/data/io/base.py
vis4d/data/io/file.py
vis4d/data/io/hdf5.py
vis4d/data/io/to_hdf5.py
vis4d/data/io/util.py
vis4d/data/io/zip.py
vis4d/data/transforms/__init__.py
vis4d/data/transforms/affine.py
vis4d/data/transforms/autoaugment.py
vis4d/data/transforms/base.py
vis4d/data/transforms/crop.py
vis4d/data/transforms/flip.py
vis4d/data/transforms/mask.py
vis4d/data/transforms/mixup.py
vis4d/data/transforms/mosaic.py
vis4d/data/transforms/normalize.py
vis4d/data/transforms/pad.py
vis4d/data/transforms/photometric.py
vis4d/data/transforms/point_sampling.py
vis4d/data/transforms/points.py
vis4d/data/transforms/post_process.py
vis4d/data/transforms/random_erasing.py
vis4d/data/transforms/resize.py
vis4d/data/transforms/select_sensor.py
vis4d-0.1.4.dist-info/licenses/LICENSE
vis4d-0.1.4.dist-info/METADATA
vis4d-0.1.4.dist-info/WHEEL
vis4d-0.1.4.dist-info/entry_points.txt
vis4d-0.1.4.dist-info/top_level.txt
vis4d-0.1.4.dist-info/RECORD
