Metadata-Version: 2.4
Name: vis4d
Version: 0.1.4
Summary: Vis4D Python package for Visual 4D scene understanding
Author: Vis4D Team
License: Apache 2.0
Project-URL: Documentation, https://vis4d.readthedocs.io
Project-URL: Source, https://github.com/syscv/vis4d
Project-URL: Tracker, https://github.com/syscv/vis4d/issues
Classifier: Programming Language :: Python :: 3
Classifier: License :: OSI Approved :: Apache Software License
Classifier: Operating System :: OS Independent
Requires-Python: >=3.11
License-File: LICENSE
Requires-Dist: absl-py
Requires-Dist: appdirs
Requires-Dist: cloudpickle
Requires-Dist: cython
Requires-Dist: devtools
Requires-Dist: h5py
Requires-Dist: jsonargparse[signatures]
Requires-Dist: lightning
Requires-Dist: ml_collections==1.1.0
Requires-Dist: numpy<2.0.0,>=1.21.0
Requires-Dist: opencv-python
Requires-Dist: pandas
Requires-Dist: pillow
Requires-Dist: plyfile
Requires-Dist: pycocotools
Requires-Dist: pydantic<2.0.0
Requires-Dist: setuptools
Requires-Dist: tensorboard
Requires-Dist: termcolor
Requires-Dist: terminaltables
Requires-Dist: timm>=0.6.0
Requires-Dist: torch>=2.0.0
Requires-Dist: torchvision>=0.15.1
Requires-Dist: tqdm
Requires-Dist: utm
Requires-Dist: wheel
Requires-Dist: scipy
Requires-Dist: scipy-stubs
Requires-Dist: bdd100k
Requires-Dist: scalabel
Requires-Dist: nuscenes-devkit
Dynamic: license-file
